setup.py
distributions_AY2020/Binomialdistribution.py
distributions_AY2020/Gaussiandistribution.py
distributions_AY2020/Generaldistribution.py
distributions_AY2020/__init__.py
distributions_AY2020.egg-info/PKG-INFO
distributions_AY2020.egg-info/SOURCES.txt
distributions_AY2020.egg-info/dependency_links.txt
distributions_AY2020.egg-info/not-zip-safe
distributions_AY2020.egg-info/top_level.txt